serp/__init__.py
serp/asm/__init__.py
serp/asm/v1.py
serp/auth/__init__.py
serp/auth/v1.py
serp/auth_token.py
serp/base.py
serp/clients.py
serp/compare/__init__.py
serp/compare/v1.py
serp/constants.py
serp/entries/__init__.py
serp/entries/v1.py
serp/groups_profiles/__init__.py
serp/groups_profiles/v1.py
serp/licenses/__init__.py
serp/licenses/v1.py
serp/liveness/__init__.py
serp/liveness/v1.py
serp/origins/__init__.py
serp/origins/v1.py
serp/profiles/__init__.py
serp/profiles/v1.py
serp/spaces/__init__.py
serp/spaces/v1.py
serp/statistics/__init__.py
serp/statistics/v1.py
serp/tokens/__init__.py
serp/tokens/access/__init__.py
serp/tokens/access/v1.py
serp/tokens/streams/__init__.py
serp/tokens/streams/v1.py
serp/users/__init__.py
serp/users/v1.py
serp/utils.py
serp/whoami/__init__.py
serp/whoami/v1.py
serp-0.1.5.dist-info/LICENSE
serp-0.1.5.dist-info/METADATA
serp-0.1.5.dist-info/WHEEL
serp-0.1.5.dist-info/RECORD
